PyTrek/AbsDisplay.py
PyTrek/AbsShip.py
PyTrek/Calculators.py
PyTrek/Console.py
PyTrek/Controls.py
PyTrek/Difficulity.py
PyTrek/ErrorCollision.py
PyTrek/Glyphs.py
PyTrek/MapGame.py
PyTrek/MapSparse.py
PyTrek/Points.py
PyTrek/PyTrek1.py
PyTrek/Quips.py
PyTrek/Reports.py
PyTrek/Sector.py
PyTrek/ShipEnterprise.py
PyTrek/ShipKlingon.py
PyTrek/ShipStarbase.py
PyTrek/TrekStrings.py
PyTrek/__init__.py
PyTrek/test_MapSparse.py
PyTrek_9000-1.0.4.dist-info/METADATA
PyTrek_9000-1.0.4.dist-info/WHEEL
PyTrek_9000-1.0.4.dist-info/top_level.txt
PyTrek_9000-1.0.4.dist-info/RECORD
