Metadata-Version: 2.1
Name: PyTrek_9000
Version: 1.0.4
Summary: Classic Cross-Platform 'StarTrek' Game
Author-email: Randall Nagy <r.a.nagy@gmail.com>
Project-URL: Homepage, https://github.com/Python3-Training/PyTrek
Project-URL: Bug Tracker, https://github.com/Python3-Training/PyTrek/issues
Classifier: Programming Language :: Python :: 3
Classifier: License :: OSI Approved :: MIT License
Classifier: Operating System :: OS Independent
Requires-Python: >=3.6
